{
  "profile": [
    {
      "name": "shubhangi p",
      "email": "motoangi.gho4@gmail.com",
      "mobile number": 848512566,
      "id": "1"
    },
    {
      "id": "9d98",
      "name": "priya",
      "email": "shubhangi.gho4@gmail.com",
      "mobile number": 85645551
    },
    {
      "id": "2311",
      "name": "shubh",
      "email": "motoangi.gho4@gmail.com",
      "mobile number": 848512566
    },
    {
      "id": "99e7",
      "name": "chintoo",
      "email": "motoangi.gho4@gmail.com",
      "mobile number": 848512566
    }
  ],
  "data": []
}